SaltDBGenerator/__init__.py
SaltDBGenerator/configure.py
SaltDBGenerator/saltGenerator.py
SaltDBGenerator-0.0.1.dist-info/METADATA
SaltDBGenerator-0.0.1.dist-info/WHEEL
SaltDBGenerator-0.0.1.dist-info/top_level.txt
SaltDBGenerator-0.0.1.dist-info/RECORD
